Metadata-Version: 2.1
Name: nkpythonlib
Version: 0.0.1
Summary: My first PyLib
Home-page: UNKNOWN
Author: Nino Kupradze
Author-email: nino.kupradze.2@gmail.com
License: MIT
Platform: UNKNOWN
Classifier: Development Status :: 5 - Production/Stable
Classifier: Intended Audience :: Education
Classifier: Operating System :: Microsoft :: Windows :: Windows 10
Classifier: License :: OSI Approved :: MIT License
Classifier: Programming Language :: Python :: 3
License-File: Licence.txt
